aurora_data_api/__init__.py
aurora_data_api/exceptions.py
aurora_data_api/mysql_error_codes.py
aurora_data_api/postgresql_error_codes.py
aurora_data_api-0.5.0.dist-info/LICENSE
aurora_data_api-0.5.0.dist-info/METADATA
aurora_data_api-0.5.0.dist-info/WHEEL
aurora_data_api-0.5.0.dist-info/top_level.txt
aurora_data_api-0.5.0.dist-info/RECORD
